xparser/__init__.py
xparser/xparser.py
xannounce_parser-0.1.0.dist-info/WHEEL
xannounce_parser-0.1.0.dist-info/entry_points.txt
xannounce_parser-0.1.0.dist-info/METADATA
xannounce_parser-0.1.0.dist-info/RECORD
