Metadata-Version: 2.3
Name: xannounce-parser
Version: 0.1.0
Summary: Add your description here
Author: provefars
Author-email: provefars <provefars@gmail.com>
Requires-Dist: lark>=1.3.0
Requires-Python: >=3.10
